fortlev_solar_sdk/__init__.py
fortlev_solar_sdk/auth.py
fortlev_solar_sdk/base_classes.py
fortlev_solar_sdk/city.py
fortlev_solar_sdk/component.py
fortlev_solar_sdk/errors.py
fortlev_solar_sdk/financing.py
fortlev_solar_sdk/fortlev_solar_client.py
fortlev_solar_sdk/order.py
fortlev_solar_sdk/responses.py
fortlev_solar_sdk/surface.py
fortlev_solar_sdk-0.2.4.dist-info/licenses/LICENSE
fortlev_solar_sdk-0.2.4.dist-info/METADATA
fortlev_solar_sdk-0.2.4.dist-info/WHEEL
fortlev_solar_sdk-0.2.4.dist-info/top_level.txt
fortlev_solar_sdk-0.2.4.dist-info/RECORD
