Metadata-Version: 2.4
Name: fortlev_solar_sdk
Version: 0.2.4
Summary: A Python SDK for interacting with the Fortlev Solar API.
Author-email: Patrick Pasquini <contatopasquini@gmail.com>
Maintainer-email: Patrick Pasquini <contatopasquini@gmail.com>
License: MIT License
Project-URL: Repository, https://github.com/patrickpasquini/fortlev_solar_sdk
Keywords: solar,API,SDK,Fortlev
Classifier: Programming Language :: Python :: 3
Classifier: Development Status :: 4 - Beta
Classifier: License :: OSI Approved :: MIT License
Classifier: Operating System :: OS Independent
Classifier: Topic :: Software Development :: Libraries :: Python Modules
Classifier: Topic :: Utilities
Classifier: Topic :: Internet :: WWW/HTTP
Classifier: Topic :: Scientific/Engineering :: Information Analysis
Classifier: Topic :: Software Development :: Libraries
Requires-Python: >=3.6
License-File: LICENSE
Requires-Dist: requests
Provides-Extra: testing
Requires-Dist: pytest; extra == "testing"
Requires-Dist: python-dotenv; extra == "testing"
Dynamic: license-file
